dummyauthenticator/__init__.py
dummyauthenticator/dummyauthenticator.py
jupyterhub_remotecsv_authenticator-0.1.dist-info/DESCRIPTION.rst
jupyterhub_remotecsv_authenticator-0.1.dist-info/METADATA
jupyterhub_remotecsv_authenticator-0.1.dist-info/RECORD
jupyterhub_remotecsv_authenticator-0.1.dist-info/WHEEL
jupyterhub_remotecsv_authenticator-0.1.dist-info/metadata.json
jupyterhub_remotecsv_authenticator-0.1.dist-info/top_level.txt
remotecsvauthenticator/__init__.py
remotecsvauthenticator/authenticator.py
