Metadata-Version: 2.0
Name: jupyterhub-remotecsv-authenticator
Version: 0.1
Summary: Remote CSV Authenticator for JupyterHub
Home-page: https://github.com/yuvipanda/jupyterhub-remotecsv-authenticator
Author: Yuvi Panda
Author-email: yuvipanda@riseup.net
License: 3 Clause BSD
Platform: UNKNOWN
